stashdb/__init__.py
stashdb/db.py
stashdb-0.0.1.dist-info/LICENSE
stashdb-0.0.1.dist-info/METADATA
stashdb-0.0.1.dist-info/WHEEL
stashdb-0.0.1.dist-info/top_level.txt
stashdb-0.0.1.dist-info/RECORD
